structure_viewer/__init__.py
structure_viewer/__main__.py
structure_viewer/cli.py
structure_viewer/colors.py
structure_viewer/config.py
structure_viewer/core.py
structure_viewer/formatters.py
structure_viewer-1.0.1.dist-info/METADATA
structure_viewer-1.0.1.dist-info/WHEEL
structure_viewer-1.0.1.dist-info/entry_points.txt
structure_viewer-1.0.1.dist-info/licenses/LICENSE
structure_viewer-1.0.1.dist-info/RECORD
