Metadata-Version: 2.4
Name: structure-viewer
Version: 1.0.1
Summary: A powerful CLI tool to visualize project directory structure with smart exclusions and multiple output formats
Project-URL: Homepage, https://github.com/crrrowz/structure-viewer
Project-URL: Repository, https://github.com/crrrowz/structure-viewer
Project-URL: Issues, https://github.com/crrrowz/structure-viewer/issues
Author: Structure Viewer Contributors
License-Expression: MIT
License-File: LICENSE
Keywords: cli,directory,files,project,structure,tree,visualization
Classifier: Development Status :: 5 - Production/Stable
Classifier: Environment :: Console
Classifier: Intended Audience :: Developers
Classifier: License :: OSI Approved :: MIT License
Classifier: Operating System :: OS Independent
Classifier: Programming Language :: Python :: 3
Classifier: Programming Language :: Python :: 3.8
Classifier: Programming Language :: Python :: 3.9
Classifier: Programming Language :: Python :: 3.10
Classifier: Programming Language :: Python :: 3.11
Classifier: Programming Language :: Python :: 3.12
Classifier: Topic :: Software Development :: Libraries :: Python Modules
Classifier: Topic :: Utilities
Requires-Python: >=3.8
Provides-Extra: dev
Requires-Dist: mypy>=1.0; extra == 'dev'
Requires-Dist: pytest-cov>=4.0; extra == 'dev'
Requires-Dist: pytest>=7.0; extra == 'dev'
Requires-Dist: pyyaml>=6.0; extra == 'dev'
Requires-Dist: ruff>=0.1.0; extra == 'dev'
Provides-Extra: yaml
Requires-Dist: pyyaml>=6.0; extra == 'yaml'
